api/__init__.py
api/main.py
component_ui/__init__.py
component_ui/component_builder.py
tests/__init__.py
tests/integration/__init__.py
tests/integration/dynamo_test.py
tests/integration/end_to_end_test.py
tests/integration/fixtures.py
tests/integration/metadata_test.py
tests/integration/settings_test.py
tests/unit/__init__.py
tests/unit/code_execution_test.py
tests/unit/dag_task_args_test.py
tests/unit/debug_transpiler.py
tests/unit/handler_test.py
tests/unit/logging_test.py
tests/unit/transpiler_test.py
typhoon/__init__.py
typhoon/cli.py
typhoon/connections.py
typhoon/handler.py
typhoon/local_config.py
typhoon/remotes.py
typhoon/shell_extensions.py
typhoon/variables.py
typhoon/watch.py
typhoon/aws/__init__.py
typhoon/aws/boto3_helper.py
typhoon/aws/dynamodb_helper.py
typhoon/aws/exceptions.py
typhoon/cli_helpers/__init__.py
typhoon/cli_helpers/cli_completion.py
typhoon/cli_helpers/json_schema.py
typhoon/cli_helpers/status.py
typhoon/contrib/__init__.py
typhoon/contrib/components/db_to_filesystem.yml
typhoon/contrib/components/db_to_snowflake.yml
typhoon/contrib/components/filesystem_to_db.yml
typhoon/contrib/components/glob_compress_and_copy.yml
typhoon/contrib/components/ifthen.yml
typhoon/contrib/components/singer_demultiplexer.yml
typhoon/contrib/functions/__init__.py
typhoon/contrib/functions/debug.py
typhoon/contrib/functions/filesystem.py
typhoon/contrib/functions/flow_control.py
typhoon/contrib/functions/http.py
typhoon/contrib/functions/json.py
typhoon/contrib/functions/shell.py
typhoon/contrib/functions/singer.py
typhoon/contrib/hooks/__init__.py
typhoon/contrib/hooks/aws_hooks.py
typhoon/contrib/hooks/debug_hooks.py
typhoon/contrib/hooks/filesystem_hooks.py
typhoon/contrib/hooks/hook_factory.py
typhoon/contrib/hooks/hook_interface.py
typhoon/contrib/hooks/http_hooks.py
typhoon/contrib/hooks/kafka_hooks.py
typhoon/contrib/hooks/singer_hook.py
typhoon/contrib/hooks/sqlalchemy_hook.py
typhoon/contrib/hooks/ssh_hooks.py
typhoon_orchestrator-0.0.58.dist-info/LICENSE
typhoon_orchestrator-0.0.58.dist-info/METADATA
typhoon_orchestrator-0.0.58.dist-info/WHEEL
typhoon_orchestrator-0.0.58.dist-info/entry_points.txt
typhoon_orchestrator-0.0.58.dist-info/top_level.txt
typhoon_orchestrator-0.0.58.dist-info/RECORD
