Metadata-Version: 2.1
Name: typhoon-orchestrator
Version: 0.0.58
Summary: Create asynchronous data pipelines and deploy to cloud or airflow
Home-page: https://github.com/typhoon-data-org/typhoon-orchestrator
Author: Typhoon Data
Author-email: info.typhoon.data@gmail.com
License: Apache 2 License
Platform: UNKNOWN
Classifier: Environment :: Console
Classifier: Operating System :: OS Independent
Classifier: Programming Language :: Python
Classifier: Programming Language :: Python :: 3.6
Requires-Dist: PyYAML
Requires-Dist: boto3
Requires-Dist: click
Requires-Dist: croniter
Requires-Dist: fs
Requires-Dist: fs-s3fs
Requires-Dist: jinja2
Requires-Dist: jsonpickle
Requires-Dist: pydantic
Requires-Dist: python-dateutil
Requires-Dist: python-dotenv
Requires-Dist: typing-extensions (>=3.7.4.3)
Requires-Dist: dataclasses ; python_version < "3.7"
Provides-Extra: all
Requires-Dist: kafka-python ; extra == 'all'
Provides-Extra: dev
Requires-Dist: datadiff ; extra == 'dev'
Requires-Dist: fastapi ; extra == 'dev'
Requires-Dist: graphviz ; extra == 'dev'
Requires-Dist: ipython ; extra == 'dev'
Requires-Dist: jedi (==0.17.2) ; extra == 'dev'
Requires-Dist: kafka-python ; extra == 'dev'
Requires-Dist: pygments ; extra == 'dev'
Requires-Dist: sqlitedict ; extra == 'dev'
Requires-Dist: streamlit ; extra == 'dev'
Requires-Dist: tabulate ; extra == 'dev'
Requires-Dist: termcolor ; extra == 'dev'
Requires-Dist: uvicorn ; extra == 'dev'
Requires-Dist: watchdog ; extra == 'dev'
Provides-Extra: test
Requires-Dist: moto ; extra == 'test'
Requires-Dist: pytest ; extra == 'test'
